hwork.py
hwork-0.0.1.dist-info/METADATA
hwork-0.0.1.dist-info/WHEEL
hwork-0.0.1.dist-info/top_level.txt
hwork-0.0.1.dist-info/RECORD
