Metadata-Version: 2.1
Name: hwork
Version: 0.0.1
Summary: Say hello!
Home-page: https://github.com/satyarth934/test_pip_pkg.git
Author: Satyarth Praveen
Author-email: sap89750@gmail.com
License: UNKNOWN
Platform: UNKNOWN
